flickr_spellcheckr
