Metadata-Version: 1.0
Name: flickr-spellcheckr
Version: 0.2.0
Summary: Commandline spellchecker for flickr photos
Home-page: https://github.com/paulcollinsiii/flickr-spellcheckr
Author: Paul Collins
Author-email: paul.collins.iii@gmail.com
License: BSD
Platform: UNKNOWN
Classifier: Development Status :: 3 - Alpha
Classifier: Environment :: Console
Classifier: Intended Audience :: Developers
Classifier: Intended Audience :: End Users/Desktop
Classifier: License :: OSI Approved :: BSD License
Classifier: Natural Language :: English
Classifier: Operating System :: Microsoft :: Windows
Classifier: Programming Language :: Python :: 2.7
Classifier: Topic :: Utilities
